fencsv.py
setup.py
fencsv.egg-info/PKG-INFO
fencsv.egg-info/SOURCES.txt
fencsv.egg-info/dependency_links.txt
fencsv.egg-info/requires.txt
fencsv.egg-info/top_level.txt