Metadata-Version: 1.1
Name: fencsv
Version: 0.0.1
Summary: convert fen strings into human readable csv and back
Home-page: https://github.com/vitiral/fencsv
Author: Garrett Berg
Author-email: vitiral@gmail.com
License: MIT
Platform: UNKNOWN
Classifier: Development Status :: 4 - Beta
Classifier: License :: OSI Approved :: MIT License
Classifier: Programming Language :: Python :: 3
Classifier: Topic :: Utilities
